rembg/__init__.py
rembg/bg.py
rembg/cmd/__init__.py
rembg/cmd/cli.py
rembg/cmd/server.py
rembg/u2net/__init__.py
rembg/u2net/data_loader.py
rembg/u2net/detect.py
rembg/u2net/u2net.py
irembg-1.0.14.dist-info/LICENSE.txt
irembg-1.0.14.dist-info/METADATA
irembg-1.0.14.dist-info/WHEEL
irembg-1.0.14.dist-info/entry_points.txt
irembg-1.0.14.dist-info/top_level.txt
irembg-1.0.14.dist-info/RECORD
