Metadata-Version: 2.1
Name: irembg
Version: 1.0.14
Summary: Remove image background
Home-page: https://github.com/danielgatis/rembg
Author: Daniel Gatis
Author-email: danielgatis@gmail.com
License: UNKNOWN
Keywords: remove,background,u2net
Platform: UNKNOWN
Classifier: License :: OSI Approved :: MIT License
Classifier: Programming Language :: Python :: 3 :: Only
Requires-Python: >=3.5, <4
Requires-Dist: flask (==1.1.2)
Requires-Dist: numpy (==1.19.1)
Requires-Dist: pillow (==7.2.0)
Requires-Dist: scikit-image (==0.17.2)
Requires-Dist: torch (==1.6.0)
Requires-Dist: torchvision (==0.7.0)
Requires-Dist: waitress (==1.4.4)
Requires-Dist: tqdm (==4.48.2)
Requires-Dist: requests (==2.24.0)
Requires-Dist: scipy (==1.5.2)
Requires-Dist: pymatting (==1.0.6)
